flake8_docstring_checker.py
flake8_docstring_checker-1.2.dist-info/LICENSE
flake8_docstring_checker-1.2.dist-info/METADATA
flake8_docstring_checker-1.2.dist-info/WHEEL
flake8_docstring_checker-1.2.dist-info/entry_points.txt
flake8_docstring_checker-1.2.dist-info/top_level.txt
flake8_docstring_checker-1.2.dist-info/RECORD
