Metadata-Version: 2.1
Name: flake8-docstring-checker
Version: 1.2
Summary: A simple flake8 plugin that checks if everything has a docstring
Author-email: JakobDev <jakobdev@gmx.de>
License: BSD-2-Clause
Project-URL: Issues, https://codeberg.org/JakobDev/flake8-docstring-checker/issues
Project-URL: Source, https://codeberg.org/JakobDev/flake8-docstring-checker
Project-URL: Donation, https://ko-fi.com/jakobdev
Keywords: JakobDev,Docstrings,flake8
Classifier: Development Status :: 5 - Production/Stable
Classifier: Intended Audience :: Developers
Classifier: Environment :: Other Environment
Classifier: License :: OSI Approved :: BSD License
Classifier: Operating System :: OS Independent
Classifier: Operating System :: POSIX
Classifier: Operating System :: POSIX :: BSD
Classifier: Operating System :: POSIX :: Linux
Classifier: Operating System :: MacOS :: MacOS X
Classifier: Operating System :: Microsoft :: Windows
Classifier: Programming Language :: Python :: 3
Classifier: Programming Language :: Python :: 3.8
Classifier: Programming Language :: Python :: 3.9
Classifier: Programming Language :: Python :: 3.10
Classifier: Programming Language :: Python :: 3.11
Classifier: Programming Language :: Python :: 3 :: Only
Classifier: Programming Language :: Python :: Implementation :: CPython
Classifier: Programming Language :: Python :: Implementation :: PyPy
Requires-Python: >=3.8
License-File: LICENSE
Requires-Dist: flake8
